{
  "name": "盾构机",
  "current": "盾构机末端部分",
  "boxes": [
    {
      "pos1": [
        -156,
        16,
        120
      ],
      "pos2": [
        -86,
        18,
        138
      ],
      "name": "主盾构机"
    },
    {
      "pos1": [
        -71,
        16,
        134
      ],
      "pos2": [
        -64,
        19,
        138
      ],
      "name": "盾构机中间部分"
    },
    {
      "pos1": [
        -79,
        16,
        133
      ],
      "pos2": [
        -73,
        19,
        138
      ],
      "name": "盾构机末端部分"
    },
    {
      "pos1": [
        -8,
        16,
        126
      ],
      "pos2": [
        12,
        18,
        144
      ],
      "name": "开路盾构机"
    }
  ]
}